diku_server/__init__.py
diku_server/tools.py
diku_server/endpoints/__init__.py
diku_server/endpoints/authentication.py
diku_server/endpoints/calendars.py
diku_server-1.0.3.dist-info/METADATA
diku_server-1.0.3.dist-info/RECORD
diku_server-1.0.3.dist-info/WHEEL
diku_server-1.0.3.dist-info/top_level.txt
